nikhil_stt/__init__.py
Nikh_stt-0.1.dist-info/METADATA
Nikh_stt-0.1.dist-info/WHEEL
Nikh_stt-0.1.dist-info/top_level.txt
Nikh_stt-0.1.dist-info/RECORD
