Metadata-Version: 2.1
Name: Nikh-stt
Version: 0.1
Summary: This is speeh to text package created by nikhil patidar
